antonnia/__init__.py
antonnia/conversations/__init__.py
antonnia/conversations/agents.py
antonnia/conversations/client.py
antonnia/conversations/exceptions.py
antonnia/conversations/messages.py
antonnia/conversations/py.typed
antonnia/conversations/sessions.py
antonnia/conversations/survey_submissions.py
antonnia/conversations/types/__init__.py
antonnia/conversations/types/agents.py
antonnia/conversations/types/conversation_tags.py
antonnia/conversations/types/conversations.py
antonnia/conversations/types/conversations_config.py
antonnia/conversations/types/messages.py
antonnia/conversations/types/session_schedules.py
antonnia/conversations/types/sessions.py
antonnia/conversations/types/survey_answers.py
antonnia/conversations/types/survey_questions.py
antonnia/conversations/types/survey_submissions.py
antonnia/conversations/types/surveys.py
antonnia/conversations/types/tags.py
antonnia/conversations/types/api/__init__.py
antonnia/conversations/types/api/agents_requests.py
antonnia/conversations/types/api/messages_requests.py
antonnia/conversations/types/api/sessions_requests.py
antonnia_conversations-2.0.39.dist-info/METADATA
antonnia_conversations-2.0.39.dist-info/WHEEL
antonnia_conversations-2.0.39.dist-info/licenses/LICENSE
antonnia_conversations-2.0.39.dist-info/RECORD
