Metadata-Version: 2.4
Name: antonnia-conversations
Version: 2.0.39
Summary: Antonnia Conversations Python SDK
Project-URL: Homepage, https://antonnia.com
Project-URL: Documentation, https://docs.antonnia.com
Project-URL: Repository, https://github.com/antonnia-com-br/antonnia-conversations
Project-URL: Bug Tracker, https://github.com/antonnia-com-br/antonnia-conversations/issues
Author-email: Antonnia <support@antonnia.com>
License: MIT
License-File: LICENSE
Keywords: antonnia,api,chat,conversations,messaging,sdk
Classifier: Development Status :: 4 - Beta
Classifier: Intended Audience :: Developers
Classifier: License :: OSI Approved :: MIT License
Classifier: Operating System :: OS Independent
Classifier: Programming Language :: Python :: 3
Classifier: Programming Language :: Python :: 3.8
Classifier: Programming Language :: Python :: 3.9
Classifier: Programming Language :: Python :: 3.10
Classifier: Programming Language :: Python :: 3.11
Classifier: Programming Language :: Python :: 3.12
Classifier: Topic :: Communications :: Chat
Classifier: Topic :: Internet :: WWW/HTTP
Classifier: Topic :: Software Development :: Libraries :: Python Modules
Requires-Python: >=3.8
Requires-Dist: httpx<1.0.0,>=0.25.0
Requires-Dist: pydantic<3.0.0,>=2.7.0
Requires-Dist: pytz>=2023.3
